{
  "question" : {
    "question_id" : 79586611,
    "title" : "How can I add a new FieldVector to an existing VectorSchemaRoot",
    "body" : "<p>In Java Apache Arrow, I have an existing <code>VectorSchemaRoot</code> that's created following <a href=\"https://arrow.apache.org/docs/java/vector_schema_root.html#vectorschemaroot\" rel=\"nofollow noreferrer\">this documentation</a>:</p>\n<pre><code>BitVector bitVector = new BitVector(&quot;boolean&quot;, allocator);\nbitVector.allocateNew();\nfor (int i = 0; i &lt; 10; i++) {\n  bitVector.setSafe(i, i % 2 == 0 ? 0 : 1);\n}\nbitVector.setValueCount(10);\n\nList&lt;Field&gt; fields = Arrays.asList(bitVector.getField());\nList&lt;FieldVector&gt; vectors = Arrays.asList(bitVector);\nVectorSchemaRoot vectorSchemaRoot = new VectorSchemaRoot(fields, vectors);\n</code></pre>\n<p>Let's say sometime in the future I need to add an additional <code>FieldVector</code> to the <code>VectorSchemaRoot</code>, how do I go about doing this? I tried using the <a href=\"https://arrow.apache.org/docs/dev/java/reference/org/apache/arrow/vector/VectorSchemaRoot.html#addVector(int,org.apache.arrow.vector.FieldVector)\" rel=\"nofollow noreferrer\">addVector method</a> but that throws an error when trying to add a new vector.</p>\n<pre><code>VarCharVector varCharVector = new VarCharVector(&quot;varchar&quot;, allocator);\nvarCharVector.allocateNew();\nfor (int i = 0; i &lt; 10; i++) {\n  varCharVector.setSafe(i, (&quot;test&quot; + i).getBytes(StandardCharsets.UTF_8));\n}\nvarCharVector.setValueCount(10);\nvectorSchemaRoot.addVector(1, varCharVector)\n</code></pre>\n",
    "tags" : [ "java", "apache-arrow" ],
    "owner" : {
      "account_id" : 3737085,
      "reputation" : 11325,
      "user_id" : 3107798,
      "user_type" : "registered",
      "accept_rate" : 50,
      "profile_image" : "https://www.gravatar.com/avatar/8c1946036d22a624bd3167099c4448c1?s=256&d=identicon&r=PG&f=y&so-version=2",
      "display_name" : "jjbskir",
      "link" : "https://stackoverflow.com/users/3107798/jjbskir"
    },
    "is_answered" : false,
    "view_count" : 39,
    "answer_count" : 0,
    "score" : 0,
    "last_activity_date" : 1745343495,
    "creation_date" : 1745329022,
    "link" : "https://stackoverflow.com/questions/79586611/how-can-i-add-a-new-fieldvector-to-an-existing-vectorschemaroot",
    "content_license" : "CC BY-SA 4.0"
  },
  "answers" : [ ],
  "question_comments" : [ {
    "comment_id" : 140357878,
    "post_id" : 79586611,
    "body" : "Looks like there may be some quirks with the addVector method - <a href=\"https://github.com/apache/arrow-java/issues/301\" rel=\"nofollow noreferrer\">github.com/apache/arrow-java/issues/301</a>",
    "score" : 0,
    "owner" : {
      "account_id" : 3737085,
      "reputation" : 11325,
      "user_id" : 3107798,
      "user_type" : "registered",
      "accept_rate" : 50,
      "profile_image" : "https://www.gravatar.com/avatar/8c1946036d22a624bd3167099c4448c1?s=256&d=identicon&r=PG&f=y&so-version=2",
      "display_name" : "jjbskir",
      "link" : "https://stackoverflow.com/users/3107798/jjbskir"
    },
    "creation_date" : 1745329093,
    "content_license" : "CC BY-SA 4.0"
  } ],
  "answer_comments" : { }
}