{
  "question" : {
    "question_id" : 79555237,
    "title" : "CXF camel : Unable to locate Spring NamespaceHandler for XML schema namespace [http://camel.apache.org/schema/cxf]",
    "body" : "<p>We have this error after migrating to jdk17 and Camel 4 :\nCaused by: org.springframework.beans.factory.parsing.BeanDefinitionParsingException: Configuration problem: Unable to locate Spring NamespaceHandler for XML schema namespace [http://camel.apache.org/schema/cxf]</p>\n<p>My file xml concerned is :</p>\n<pre><code>&lt;?xml version=&quot;1.0&quot; encoding=&quot;UTF-8&quot;?&gt;\n&lt;beans xmlns=&quot;http://www.springframework.org/schema/beans&quot;\n       xmlns:context=&quot;http://www.springframework.org/schema/context&quot;\n       xmlns:util=&quot;http://www.springframework.org/schema/util&quot;\n       xmlns:xsi=&quot;http://www.w3.org/2001/XMLSchema-instance&quot;\n       xmlns:camel=&quot;http://camel.apache.org/schema/spring&quot;\n       xmlns:cxf=&quot;http://camel.apache.org/schema/cxf&quot;\n       xmlns:soap=&quot;http://cxf.apache.org/bindings/soap&quot;\n       xsi:schemaLocation=&quot;http://www.springframework.org/schema/beans http://www.springframework.org/schema/beans/spring-beans.xsd\n            http://www.springframework.org/schema/context http://www.springframework.org/schema/context/spring-context.xsd\n            http://www.springframework.org/schema/util http://www.springframework.org/schema/util/spring-util.xsd\n            http://camel.apache.org/schema/spring http://camel.apache.org/schema/spring/camel-spring.xsd\n            http://camel.apache.org/schema/cxf http://camel.apache.org/schema/cxf/camel-cxf.xsd\n            http://cxf.apache.org/bindings/soap \n            https://cxf.apache.org/bindings/schemas/configuration/soap.xsd\n            &quot;&gt;\n   &lt;!-- soap end point --&gt;    \n    &lt;cxf:cxfEndpoint id=&quot;interfaceSoap&quot;\n            address=&quot;${path}&quot; \n            serviceClass=&quot;myClass&quot;&gt;\n          &lt;cxf:properties&gt;\n                 &lt;entry key=&quot;schema-validation-enabled&quot; value=&quot;true&quot; /&gt;\n          &lt;/cxf:properties&gt;\n          &lt;cxf:inInterceptors&gt;\n             &lt;bean class=&quot;myInInterceptor&quot;/&gt;\n          &lt;/cxf:inInterceptors&gt;\n          &lt;cxf:outInterceptors&gt;\n             &lt;bean class=&quot;myOutInterceptor&quot;/&gt;\n          &lt;/cxf:outInterceptors&gt;\n    &lt;/cxf:cxfEndpoint&gt;\n</code></pre>\n<p>and I have already libs camel cxf in my pom (camel 4.0.2) :</p>\n<pre><code>    &lt;dependency&gt;\n        &lt;groupId&gt;org.apache.camel&lt;/groupId&gt;\n        &lt;artifactId&gt;camel-api&lt;/artifactId&gt;\n    &lt;/dependency&gt;\n    &lt;dependency&gt;\n        &lt;groupId&gt;org.apache.camel&lt;/groupId&gt;\n        &lt;artifactId&gt;camel-jms&lt;/artifactId&gt;\n    &lt;/dependency&gt;\n    &lt;dependency&gt;\n        &lt;groupId&gt;org.apache.camel&lt;/groupId&gt;\n        &lt;artifactId&gt;camel-spring&lt;/artifactId&gt;\n    &lt;/dependency&gt;\n    &lt;dependency&gt;\n        &lt;groupId&gt;org.apache.camel&lt;/groupId&gt;\n        &lt;artifactId&gt;camel-spring-xml&lt;/artifactId&gt;\n    &lt;/dependency&gt;\n    &lt;dependency&gt;\n        &lt;groupId&gt;org.apache.camel&lt;/groupId&gt;\n        &lt;artifactId&gt;camel-core&lt;/artifactId&gt;\n    &lt;/dependency&gt;       \n\n    &lt;dependency&gt;\n        &lt;groupId&gt;org.apache.camel&lt;/groupId&gt;\n        &lt;artifactId&gt;camel-jaxb&lt;/artifactId&gt;\n    &lt;/dependency&gt;\n    &lt;dependency&gt;\n        &lt;groupId&gt;org.apache.camel&lt;/groupId&gt;\n        &lt;artifactId&gt;camel-support&lt;/artifactId&gt;\n    &lt;/dependency&gt;       \n    &lt;dependency&gt;\n        &lt;groupId&gt;org.apache.camel&lt;/groupId&gt;\n        &lt;artifactId&gt;camel-cxf-rest&lt;/artifactId&gt;\n    &lt;/dependency&gt;   \n    &lt;dependency&gt;\n        &lt;groupId&gt;org.apache.camel&lt;/groupId&gt;\n        &lt;artifactId&gt;camel-cxf-common&lt;/artifactId&gt;\n    &lt;/dependency&gt;\n    &lt;dependency&gt;\n        &lt;groupId&gt;org.apache.camel&lt;/groupId&gt;\n        &lt;artifactId&gt;camel-soap&lt;/artifactId&gt;\n    &lt;/dependency&gt;\n    &lt;dependency&gt;\n        &lt;groupId&gt;org.apache.camel&lt;/groupId&gt;\n        &lt;artifactId&gt;camel-cxf-soap&lt;/artifactId&gt;\n    &lt;/dependency&gt;\n    &lt;dependency&gt;\n           &lt;groupId&gt;org.apache.cxf&lt;/groupId&gt;\n           &lt;artifactId&gt;cxf-rt-frontend-jaxws&lt;/artifactId&gt;\n    &lt;/dependency&gt;\n    \n    \n    &lt;dependency&gt;\n        &lt;groupId&gt;org.opengis.cite.xerces&lt;/groupId&gt;\n        &lt;artifactId&gt;xercesImpl-xsd11&lt;/artifactId&gt;\n        &lt;version&gt;2.12-beta-r1667115&lt;/version&gt;\n    &lt;/dependency&gt;\n    \n    &lt;!-- Utils --&gt;\n    &lt;dependency&gt;\n        &lt;groupId&gt;org.aspectj&lt;/groupId&gt;\n        &lt;artifactId&gt;aspectjweaver&lt;/artifactId&gt;\n    &lt;/dependency&gt;\n    &lt;dependency&gt;\n        &lt;groupId&gt;org.apache.commons&lt;/groupId&gt;\n        &lt;artifactId&gt;commons-lang3&lt;/artifactId&gt;\n    &lt;/dependency&gt;\n    &lt;dependency&gt;\n        &lt;groupId&gt;org.apache.commons&lt;/groupId&gt;\n        &lt;artifactId&gt;commons-collections4&lt;/artifactId&gt;\n    &lt;/dependency&gt;\n    &lt;dependency&gt;\n        &lt;groupId&gt;commons-collections&lt;/groupId&gt;\n        &lt;artifactId&gt;commons-collections&lt;/artifactId&gt;\n    &lt;/dependency&gt;\n</code></pre>\n<p>Could you give us advice? which lib is missing ?</p>\n",
    "tags" : [ "java", "spring", "apache-camel", "tomcat10" ],
    "owner" : {
      "account_id" : 7638143,
      "reputation" : 53,
      "user_id" : 5791095,
      "user_type" : "registered",
      "profile_image" : "https://www.gravatar.com/avatar/dd926f304fa1f83df70a13db750c32cb?s=256&d=identicon&r=PG&f=y&so-version=2",
      "display_name" : "cs_zineb",
      "link" : "https://stackoverflow.com/users/5791095/cs-zineb"
    },
    "is_answered" : true,
    "view_count" : 77,
    "answer_count" : 1,
    "score" : 0,
    "last_activity_date" : 1743784163,
    "creation_date" : 1743767579,
    "link" : "https://stackoverflow.com/questions/79555237/cxf-camel-unable-to-locate-spring-namespacehandler-for-xml-schema-namespace-h",
    "content_license" : "CC BY-SA 4.0"
  },
  "answers" : [ {
    "answer_id" : 79555861,
    "question_id" : 79555237,
    "body" : "<p>I resolved the problem with this :</p>\n<p><em><a href=\"http://camel.apache.org/schema/cxf/jaxws\" rel=\"nofollow noreferrer\">http://camel.apache.org/schema/cxf/jaxws</a> <a href=\"http://camel.apache.org/schema/cxf/jaxws/camel-cxf.xsd\" rel=\"nofollow noreferrer\">http://camel.apache.org/schema/cxf/jaxws/camel-cxf.xsd</a></em></p>\n<p>and with adding this lib to pom :  camel-cxf-spring-rest, camel-cxf-spring-soap</p>\n<p><a href=\"https://camel.apache.org/manual/camel-3x-upgrade-guide-3_18.html#_camel_cxf\" rel=\"nofollow noreferrer\">https://camel.apache.org/manual/camel-3x-upgrade-guide-3_18.html#_camel_cxf</a></p>\n",
    "score" : 1,
    "is_accepted" : true,
    "owner" : {
      "account_id" : 7638143,
      "reputation" : 53,
      "user_id" : 5791095,
      "user_type" : "registered",
      "profile_image" : "https://www.gravatar.com/avatar/dd926f304fa1f83df70a13db750c32cb?s=256&d=identicon&r=PG&f=y&so-version=2",
      "display_name" : "cs_zineb",
      "link" : "https://stackoverflow.com/users/5791095/cs-zineb"
    },
    "creation_date" : 1743784163,
    "last_activity_date" : 1743784163,
    "content_license" : "CC BY-SA 4.0"
  } ],
  "question_comments" : [ ],
  "answer_comments" : { }
}