{
  "question" : {
    "question_id" : 79550037,
    "title" : "NoClassDefFoundError: Failed resolution of: Lkotlin/enums/EnumEntriesKt",
    "body" : "<p>After upgrading my project to use the new rtc-engine and version 2.9 of the UI, I encountered the following error:</p>\n<pre><code>java.lang.NoClassDefFoundError: Failed resolution of: Lkotlin/enums/EnumEntriesKt;\n</code></pre>\n<p>What is the recommended way to resolve this error?</p>\n",
    "tags" : [ "java", "android", "kotlin", "callkit", "trtc.io" ],
    "owner" : {
      "account_id" : 34767832,
      "reputation" : 39,
      "user_id" : 26765275,
      "user_type" : "registered",
      "profile_image" : "https://www.gravatar.com/avatar/3813686b5b5c85ca053c46a94c790f7c?s=256&d=identicon&r=PG&f=y&so-version=2",
      "display_name" : " AstralWanderer",
      "link" : "https://stackoverflow.com/users/26765275/astralwanderer"
    },
    "is_answered" : true,
    "view_count" : 955,
    "closed_date" : 1757157601,
    "answer_count" : 2,
    "score" : 1,
    "last_activity_date" : 1744252558,
    "creation_date" : 1743581078,
    "link" : "https://stackoverflow.com/questions/79550037/noclassdeffounderror-failed-resolution-of-lkotlin-enums-enumentrieskt",
    "closed_reason" : "Not suitable for this site"
  },
  "answers" : [ {
    "answer_id" : 79550601,
    "question_id" : 79550037,
    "body" : "<p>The EnumEntriesKt class is part of Kotlin's support for the Enum.entries property, That was introduced in Kotlin 1.8.0. If your project or one of its dependencies (e.g., rtc-engine or UI version 2.9) uses this feature, you need to ensure that your project is using Kotlin 1.8.0 or later version.</p>\n<p>Open your build.gradle file (or build.gradle.kts if you're using Kotlin DSL).<br />\nUpdate the Kotlin version in the plugins block or buildscript block.<br />\nIf you're using the plugins block:</p>\n<pre><code>\n\nplugins {\n    id &quot;org.jetbrains.kotlin.jvm&quot; version &quot;1.8.22&quot; // Use the latest compatible version\n}\n</code></pre>\n<p>If you're using the buildscript block:</p>\n<pre><code>\nbuildscript {\n    ext.kotlin_version = &quot;1.8.22&quot; // Use the latest compatible version\n    repositories {\n        google()\n        mavenCentral()\n    }\n    dependencies {\n        classpath &quot;org.jetbrains.kotlin:kotlin-gradle-plugin:$kotlin_version&quot;\n    }\n}\n</code></pre>\n",
    "score" : 2,
    "is_accepted" : false,
    "owner" : {
      "account_id" : 10927511,
      "reputation" : 3218,
      "user_id" : 8031784,
      "user_type" : "registered",
      "profile_image" : "https://i.sstatic.net/ikcJL.png?s=256",
      "display_name" : "Aniruddh Parihar",
      "link" : "https://stackoverflow.com/users/8031784/aniruddh-parihar"
    },
    "creation_date" : 1743596141,
    "last_activity_date" : 1743596141,
    "content_license" : "CC BY-SA 4.0"
  }, {
    "answer_id" : 79565636,
    "question_id" : 79550037,
    "body" : "<p>The NoClassDefFoundError for EnumEntriesKt occurs because the new UI version 2.9 requires Kotlin version 1.8.20 or higher.</p>\n<p>Update the Kotlin plugin version in your project’s root build.gradle file to at least 1.8.20 (or higher, such as 1.9.0).</p>\n<p>Apply the Kotlin plugin in your app’s build.gradle file:</p>\n<p>```</p>\n<p>apply plugin: 'org.jetbrains.kotlin.android'</p>\n<p>```</p>\n",
    "score" : 1,
    "is_accepted" : false,
    "owner" : {
      "account_id" : 41291037,
      "reputation" : 11,
      "user_id" : 30218816,
      "user_type" : "registered",
      "profile_image" : "https://www.gravatar.com/avatar/10d2e29e7b0950e90d8be8d031926067?s=256&d=identicon&r=PG&f=y&so-version=2",
      "display_name" : "bob bob",
      "link" : "https://stackoverflow.com/users/30218816/bob-bob"
    },
    "creation_date" : 1744252558,
    "last_activity_date" : 1744252558,
    "content_license" : "CC BY-SA 4.0"
  } ],
  "question_comments" : [ {
    "comment_id" : 140289662,
    "post_id" : 79550037,
    "body" : "Please <a href=\"https://stackoverflow.com/posts/79550037/edit\">edit</a> the question to provide a <a href=\"https://stackoverflow.com/help/minimal-reproducible-example\">minimal reproducible example</a>.",
    "score" : 0,
    "owner" : {
      "account_id" : 8120254,
      "reputation" : 21086,
      "user_id" : 6216216,
      "user_type" : "registered",
      "profile_image" : "https://www.gravatar.com/avatar/e8c2dc279acf2025292412366e8eb72a?s=256&d=identicon&r=PG&f=y&so-version=2",
      "display_name" : "tyg",
      "link" : "https://stackoverflow.com/users/6216216/tyg"
    },
    "creation_date" : 1743586103,
    "content_license" : "CC BY-SA 4.0"
  }, {
    "comment_id" : 140289514,
    "post_id" : 79550037,
    "body" : "In order to have a better chance at getting your question answered, it may be helpful to provide more information about what you are trying to do and what you have already tried.",
    "score" : 0,
    "owner" : {
      "account_id" : 1008797,
      "reputation" : 1568,
      "user_id" : 1021835,
      "user_type" : "registered",
      "accept_rate" : 89,
      "profile_image" : "https://www.gravatar.com/avatar/0ef0e0a1a0f4f593da629b4214b32578?s=256&d=identicon&r=PG",
      "display_name" : "Mark Tielemans",
      "link" : "https://stackoverflow.com/users/1021835/mark-tielemans"
    },
    "creation_date" : 1743584077,
    "content_license" : "CC BY-SA 4.0"
  } ],
  "answer_comments" : { }
}