{
  "question" : {
    "question_id" : 79736445,
    "title" : "VSCode Maven for Java can&#39;t create Maven project",
    "body" : "<p>When i creating project with Ctrl+Shift+P -&gt; Java: Create Java Project -&gt; any archetype -&gt;... I got an error:</p>\n<p><code>Executing task: &quot;mvn org.apache.maven.plugins:maven-archetype-plugin:3.1.2:generate -DarchetypeArtifactId=&quot;maven-archetype-quickstart&quot; -DarchetypeGroupId=&quot;org.apache.maven.archetypes&quot; -DarchetypeVersion=&quot;1.4&quot; -DgroupId=&quot;com.example&quot; -DartifactId=&quot;demo&quot;&quot; </code></p>\n<p><code>There is a syntax error in the file name, folder name, or volume label.</code></p>\n<p>and</p>\n<p><code>*  The terminal process &quot;cmd.exe /c &quot;&quot;mvn org.apache.maven.plugins:maven-archetype-plugin:3.1.2:generate -DarchetypeArtifactId=&quot;maven-archetype-quickstart&quot; -DarchetypeGroupId=&quot;org.apache.maven.archetypes&quot; -DarchetypeVersion=&quot;1.4&quot; -DgroupId=&quot;com.example&quot; -DartifactId=&quot;demo&quot;&quot;&quot;&quot; terminated with exit code: 1.</code></p>\n<p><code>*  Terminal will be reused by tasks, press any key to close it.</code></p>\n<p>The problem is in the extra quotes that vscode adds for some reason</p>\n<p>For example:\n<code>mvn org.apache.maven.plugins:maven-archetype-plugin:3.1.2:generate -DarchetypeArtifactId=&quot;maven-archetype-quickstart&quot; -DarchetypeGroupId=&quot;org.apache.maven.archetypes&quot; -DarchetypeVersion=&quot;1.4&quot; -DgroupId=&quot;com.example&quot; -DartifactId=&quot;demo&quot;</code> - works fine</p>\n<p>What needs to be done, what settings to change, to get rid of unnecessary quotes?</p>\n",
    "tags" : [ "java", "maven", "visual-studio-code" ],
    "owner" : {
      "account_id" : 32655623,
      "reputation" : 33,
      "user_id" : 25377987,
      "user_type" : "registered",
      "profile_image" : "https://www.gravatar.com/avatar/5bbd5f7183ebfa7ed01d6c533c6e4ba7?s=256&d=identicon&r=PG&f=y&so-version=2",
      "display_name" : "Shalapai2004",
      "link" : "https://stackoverflow.com/users/25377987/shalapai2004"
    },
    "is_answered" : false,
    "view_count" : 182,
    "answer_count" : 1,
    "score" : 0,
    "last_activity_date" : 1758707692,
    "creation_date" : 1755262673,
    "link" : "https://stackoverflow.com/questions/79736445/vscode-maven-for-java-cant-create-maven-project",
    "content_license" : "CC BY-SA 4.0"
  },
  "answers" : [ {
    "answer_id" : 79773549,
    "question_id" : 79736445,
    "body" : "<p>Was struggling today with the same issue. Link in comment to OP didnt work, but I managed to fix my case myself and here is how I did it for anyone seeking:<br />\n1. In my settings for VSCode extension of Maven path to mvn has been as &quot;{DISK}:/{MavenFolder}/bin&quot;<br />\n2. I edited it to &quot;{DISK}:/{MavenFolder}/bin/mvn&quot; and everything works fine!</p>\n<p>PS: Dont forget to download and unpack maven from official site somewhere</p>\n",
    "score" : 0,
    "is_accepted" : false,
    "owner" : {
      "account_id" : 23115037,
      "reputation" : 1,
      "user_id" : 17222435,
      "user_type" : "registered",
      "profile_image" : "https://lh3.googleusercontent.com/a-/AOh14GhLYUg7OzFHhxf04sCqYIq_tTD7Ov0pVcfiFC2N=k-s256",
      "display_name" : "dolokox",
      "link" : "https://stackoverflow.com/users/17222435/dolokox"
    },
    "creation_date" : 1758707568,
    "last_activity_date" : 1758707692,
    "content_license" : "CC BY-SA 4.0"
  } ],
  "question_comments" : [ {
    "comment_id" : 140668144,
    "post_id" : 79736445,
    "body" : "The bug is using Visual Studio Code when literally every Java oriented IDE out there, IntelliJ IDEA most notably, is designed for the job and will give zero head aches.",
    "score" : 1,
    "owner" : {
      "account_id" : 187094,
      "reputation" : 5301,
      "user_id" : 424903,
      "user_type" : "registered",
      "profile_image" : "https://i.sstatic.net/8oHZF.png?s=256",
      "display_name" : "Gimby",
      "link" : "https://stackoverflow.com/users/424903/gimby"
    },
    "creation_date" : 1755264492,
    "content_license" : "CC BY-SA 4.0"
  }, {
    "comment_id" : 140668116,
    "post_id" : 79736445,
    "body" : "Duplicate: <a href=\"https://stackoverflow.com/questions/79732285/error-creating-java-project-with-vs-code-and-maven\">Error creating java project with VS Code and Maven</a>; the answer there suggests it&#39;s a bug in the extension used.",
    "score" : 1,
    "owner" : {
      "account_id" : 213468,
      "reputation" : 110280,
      "user_id" : 466862,
      "user_type" : "registered",
      "profile_image" : "https://www.gravatar.com/avatar/d873f397779db38cd510d9ee5416fd43?s=256&d=identicon&r=PG",
      "display_name" : "Mark Rotteveel",
      "link" : "https://stackoverflow.com/users/466862/mark-rotteveel"
    },
    "creation_date" : 1755263437,
    "content_license" : "CC BY-SA 4.0"
  } ],
  "answer_comments" : { }
}